event/__init__.py
tests/__init__.py
tests/test_event.py
tests/test_upgrader.py
pevl-0.0.3.dist-info/LICENSE
pevl-0.0.3.dist-info/METADATA
pevl-0.0.3.dist-info/WHEEL
pevl-0.0.3.dist-info/top_level.txt
pevl-0.0.3.dist-info/RECORD
