Metadata-Version: 2.1
Name: pevl
Version: 0.0.3
Summary: Library to handle versions for events
Home-page: https://github.com/silarsis/pevl
Author: Kevin Littlejohn
Author-email: kevin@littlejohn.id.au
License: UNKNOWN
Keywords: event sourcing versioning
Platform: UNKNOWN
Requires-Python: >=3.8
License-File: LICENSE
